odoo10_addon_pos_order_mgmt-10.0.1.0.3.99.dev5-py3.8-nspkg.pth
odoo/addons/pos_order_mgmt/README.rst
odoo/addons/pos_order_mgmt/__init__.py
odoo/addons/pos_order_mgmt/__manifest__.py
odoo/addons/pos_order_mgmt/i18n/es.po
odoo/addons/pos_order_mgmt/i18n/fr.po
odoo/addons/pos_order_mgmt/i18n/it.po
odoo/addons/pos_order_mgmt/i18n/pos_order_mgmt.pot
odoo/addons/pos_order_mgmt/models/__init__.py
odoo/addons/pos_order_mgmt/models/pos_config.py
odoo/addons/pos_order_mgmt/models/pos_order.py
odoo/addons/pos_order_mgmt/readme/CONFIGURE.rst
odoo/addons/pos_order_mgmt/readme/CONTRIBUTORS.rst
odoo/addons/pos_order_mgmt/readme/DESCRIPTION.rst
odoo/addons/pos_order_mgmt/readme/ROADMAP.rst
odoo/addons/pos_order_mgmt/readme/USAGE.rst
odoo/addons/pos_order_mgmt/static/description/icon.png
odoo/addons/pos_order_mgmt/static/description/index.html
odoo/addons/pos_order_mgmt/static/description/order-mgmt-config.png
odoo/addons/pos_order_mgmt/static/description/order-mgmt-icon.png
odoo/addons/pos_order_mgmt/static/description/order-mgmt-list.png
odoo/addons/pos_order_mgmt/static/src/css/pos.css
odoo/addons/pos_order_mgmt/static/src/js/models.js
odoo/addons/pos_order_mgmt/static/src/js/widgets.js
odoo/addons/pos_order_mgmt/static/src/xml/pos.xml
odoo/addons/pos_order_mgmt/tests/__init__.py
odoo/addons/pos_order_mgmt/tests/test_module.py
odoo/addons/pos_order_mgmt/views/assets.xml
odoo/addons/pos_order_mgmt/views/view_pos_config.xml
odoo/addons/pos_order_mgmt/views/view_pos_order.xml
odoo10_addon_pos_order_mgmt-10.0.1.0.3.99.dev5.dist-info/METADATA
odoo10_addon_pos_order_mgmt-10.0.1.0.3.99.dev5.dist-info/WHEEL
odoo10_addon_pos_order_mgmt-10.0.1.0.3.99.dev5.dist-info/namespace_packages.txt
odoo10_addon_pos_order_mgmt-10.0.1.0.3.99.dev5.dist-info/top_level.txt
odoo10_addon_pos_order_mgmt-10.0.1.0.3.99.dev5.dist-info/RECORD
